bgtasks/__init__.py
bgtasks/__main__.py
bgtasks/admin.py
bgtasks/amqp.py
bgtasks/apps.py
bgtasks/config.py
bgtasks/constants.py
bgtasks/job.py
bgtasks/models.py
bgtasks/rpc.py
bgtasks/transaction.py
bgtasks/views.py
bgtasks/management/__init__.py
bgtasks/management/commands/__init__.py
bgtasks/management/commands/tasks.py
bgtasks/migrations/__init__.py
bgtasks/rest_framework/__init__.py
bgtasks/rest_framework/fields.py
bgtasks/rest_framework/filters.py
bgtasks/rest_framework/response.py
bgtasks/rest_framework/serilaizers.py
bgtasks/tests/__init__.py
bgtasks/tests/test_rest.py
bgtasks/tests/test_util.py
bgtasks/utils/__init__.py
bgtasks/utils/const.py
bgtasks/utils/merge.py
bgtasks/utils/rpc_response.py
settings/__init__.py
settings/settings.py
settings/urls.py
settings/wsgi.py
testapp/__init__.py
testapp/admin.py
testapp/apps.py
testapp/models.py
testapp/tests.py
testapp/views.py
testapp/migrations/0001_initial.py
testapp/migrations/0002_category.py
testapp/migrations/__init__.py
bgtasks-0.0.44.dist-info/LICENSE
bgtasks-0.0.44.dist-info/METADATA
bgtasks-0.0.44.dist-info/WHEEL
bgtasks-0.0.44.dist-info/top_level.txt
bgtasks-0.0.44.dist-info/RECORD
