Metadata-Version: 2.1
Name: bgtasks
Version: 0.0.44
Summary: Microservice with django
Home-page: https://github.com/myrubapa/bgtasks
Author: Bekhzod Tillakhanov
Author-email: bekhzod.tillakhanov@gmail.com
License: UNKNOWN
Platform: UNKNOWN
Classifier: Programming Language :: Python :: 3
Classifier: License :: OSI Approved :: MIT License
Classifier: Operating System :: OS Independent
Requires-Python: >=3.5
Requires-Dist: pika
